collective/contact_behaviors/__init__.py
collective/contact_behaviors/configure.zcml
collective/contact_behaviors/interfaces.py
collective/contact_behaviors/permissions.zcml
collective/contact_behaviors/profiles.zcml
collective/contact_behaviors/testing.py
collective/contact_behaviors/behaviors/__init__.py
collective/contact_behaviors/behaviors/address_info.py
collective/contact_behaviors/behaviors/configure.zcml
collective/contact_behaviors/behaviors/contact_info.py
collective/contact_behaviors/locales/__main__.py
collective/contact_behaviors/locales/collective.contact_behaviors.pot
collective/contact_behaviors/locales/iso_3166-1.pot
collective/contact_behaviors/locales/de/LC_MESSAGES/collective.contact_behaviors.po
collective/contact_behaviors/locales/de/LC_MESSAGES/iso_3166-1.po
collective/contact_behaviors/locales/es/LC_MESSAGES/collective.contact_behaviors.po
collective/contact_behaviors/locales/es/LC_MESSAGES/iso_3166-1.po
collective/contact_behaviors/locales/fi/LC_MESSAGES/collective.contact_behaviors.po
collective/contact_behaviors/locales/fi/LC_MESSAGES/iso_3166-1.po
collective/contact_behaviors/locales/fr/LC_MESSAGES/collective.contact_behaviors.po
collective/contact_behaviors/locales/fr/LC_MESSAGES/iso_3166-1.po
collective/contact_behaviors/locales/nl/LC_MESSAGES/collective.contact_behaviors.po
collective/contact_behaviors/locales/nl/LC_MESSAGES/iso_3166-1.po
collective/contact_behaviors/locales/pt_BR/LC_MESSAGES/collective.contact_behaviors.po
collective/contact_behaviors/locales/pt_BR/LC_MESSAGES/iso_3166-1.po
collective/contact_behaviors/profiles/default/catalog.xml
collective/contact_behaviors/profiles/default/metadata.xml
collective/contact_behaviors/profiles/default/rolemap.xml
collective/contact_behaviors/profiles/default/registry/collective.contact_behaviors.interfaces.IContactBehaviors.xml
collective/contact_behaviors/profiles/default/registry/plone.app.querystring.interfaces.IQueryField.xml
collective_contact_behaviors-1.0.0b5.dist-info/METADATA
collective_contact_behaviors-1.0.0b5.dist-info/WHEEL
collective_contact_behaviors-1.0.0b5.dist-info/entry_points.txt
collective_contact_behaviors-1.0.0b5.dist-info/licenses/LICENSE.md
collective_contact_behaviors-1.0.0b5.dist-info/RECORD
