Metadata-Version: 2.4
Name: collective.contact_behaviors
Version: 1.0.0b5
Summary: A collection of contact information behaviors and vocabularies for Dexterity content types.
Project-URL: Changelog, https://github.com/collective/collective.contact_behaviors/blob/main/CHANGELOG.md
Project-URL: Homepage, https://github.com/collective/collective.contact_behaviors
Project-URL: Issues, https://github.com/collective/collective.contact_behaviors/issues
Project-URL: Repository, https://github.com/collective/collective.contact_behaviors/
Author-email: Érico Andrei <ericof@plone.org>
License: GNU General Public License v2 (GPLv2)
License-File: LICENSE.md
Keywords: Plone,Python
Classifier: Development Status :: 5 - Production/Stable
Classifier: Environment :: Web Environment
Classifier: Framework :: Plone
Classifier: Framework :: Plone :: 6.0
Classifier: Framework :: Plone :: 6.1
Classifier: Framework :: Plone :: Addon
Classifier: Framework :: Zope
Classifier: Framework :: Zope :: 5
Classifier: License :: OSI Approved :: GNU General Public License v2 (GPLv2)
Classifier: Programming Language :: Python
Classifier: Programming Language :: Python :: 3 :: Only
Classifier: Programming Language :: Python :: 3.10
Classifier: Programming Language :: Python :: 3.11
Classifier: Programming Language :: Python :: 3.12
Classifier: Programming Language :: Python :: 3.13
Requires-Python: >=3.10
Requires-Dist: plone-api
Requires-Dist: plone-restapi
Requires-Dist: products-cmfplone>=6.0.0
Requires-Dist: pycountry
Provides-Extra: test
Requires-Dist: collective-mockmailhost; extra == 'test'
Requires-Dist: horse-with-no-namespace; extra == 'test'
Requires-Dist: plone-app-robotframework[debug]; extra == 'test'
Requires-Dist: plone-app-testing; extra == 'test'
Requires-Dist: plone-restapi[test]; extra == 'test'
Requires-Dist: pytest-cov; extra == 'test'
Requires-Dist: pytest-plone>=1.0.0a1; extra == 'test'
Requires-Dist: zest-releaser[recommended]; extra == 'test'
Requires-Dist: zest-releaser[recommended]>=9.5.0; extra == 'test'
Requires-Dist: zestreleaser-towncrier>=1.3.0; extra == 'test'
